LICENSE.rst
LICENSE_GPL.rst
MANIFEST.in
README.rst
setup.py
src/agx/__init__.py
src/agx.generator.generator.egg-info/PKG-INFO
src/agx.generator.generator.egg-info/SOURCES.txt
src/agx.generator.generator.egg-info/dependency_links.txt
src/agx.generator.generator.egg-info/entry_points.txt
src/agx.generator.generator.egg-info/namespace_packages.txt
src/agx.generator.generator.egg-info/not-zip-safe
src/agx.generator.generator.egg-info/requires.txt
src/agx.generator.generator.egg-info/top_level.txt
src/agx/generator/__init__.py
src/agx/generator/generator/__init__.py
src/agx/generator/generator/configure.zcml
src/agx/generator/generator/generator.py
src/agx/generator/generator/profilelocation.py
src/agx/generator/generator/scope.py
src/agx/generator/generator/profiles/generator.profile.di
src/agx/generator/generator/profiles/generator.profile.notation
src/agx/generator/generator/profiles/generator.profile.uml
src/agx/generator/generator/resources/model_templates/generator_example/manifest.txt
src/agx/generator/generator/resources/model_templates/generator_example/model.di
src/agx/generator/generator/resources/model_templates/generator_example/model.notation
src/agx/generator/generator/resources/model_templates/generator_example/model.uml
src/agx/generator/generator/resources/model_templates/generator_example/model.uml.agx
src/agx/generator/generator/resources/model_templates/generator_example/uml_profiles/generator.profile.uml
src/agx/generator/generator/resources/model_templates/generator_example/uml_profiles/pyegg.profile.uml
src/agx/generator/generator/resources/model_templates/generator_example/uml_profiles/zca.profile.uml
src/agx/generator/generator/resources/vanilla_profile/model.profile.di
src/agx/generator/generator/resources/vanilla_profile/model.profile.notation
src/agx/generator/generator/resources/vanilla_profile/model.profile.uml
src/agx/generator/generator/testing/__init__.py
src/agx/generator/generator/testing/data/model.di
src/agx/generator/generator/testing/data/model.notation
src/agx/generator/generator/testing/data/model.uml
src/agx/generator/generator/testing/data/model.uml.agx
src/agx/generator/generator/testing/data/uml_profiles/pyegg.profile.uml
src/agx/generator/generator/testing/data/uml_profiles/pyegg.profile.uml.agx
src/agx/generator/generator/testing/data/uml_profiles/zca.profile.uml